README.md
setup.py
xlframe/__init__.py
xlframe/style.py
xlframe/utils.py
xlframe/xlframe.py
xlframe.egg-info/PKG-INFO
xlframe.egg-info/SOURCES.txt
xlframe.egg-info/dependency_links.txt
xlframe.egg-info/requires.txt
xlframe.egg-info/top_level.txt