Metadata-Version: 1.1
Name: xlframe
Version: 0.0.4
Summary: A Python library for styling dataframes when exporting to excel.
Home-page: https://github.com/Doichfndgv/xlframe
Author: Doichfndgv
Author-email: Doichfndgv@gmail.com
License: UNKNOWN
Platform: UNKNOWN
Classifier: Development Status :: 4 - Beta
Classifier: Intended Audience :: Developers
Classifier: License :: OSI Approved :: MIT License
Classifier: Programming Language :: Python :: 3
Classifier: Programming Language :: Python :: 3.5
Classifier: Programming Language :: Python :: 3.6
Classifier: Programming Language :: Python :: 3.7
